throttle/__init__.py
throttle/schedules.py
throttle-0.2.2.dist-info/LICENCE
throttle-0.2.2.dist-info/METADATA
throttle-0.2.2.dist-info/WHEEL
throttle-0.2.2.dist-info/top_level.txt
throttle-0.2.2.dist-info/RECORD
