Metadata-Version: 2.1
Name: throttle
Version: 0.2.2
Summary: Frequency tracking and throttling utilities.
Home-page: https://github.com/Exahilosys/throttle
Author: Exahilosys
License: MIT
Platform: UNKNOWN
Provides-Extra: docs
